{
  "schema": "broadcast_board/v1",
  "mode": "open",
  "game": "rushn_attack",
  "mission": "m1",
  "model_version": "gen0",
  "prev_model_version": null,
  "frontier": {
    "max_checkpoint": -1,
    "death_wall": null
  },
  "eval": {
    "episodes": 0,
    "frontier_cp": -1,
    "mission_clear_rate": 0.0,
    "reach_cp": {},
    "death_wall": null
  },
  "delta": {
    "available": false,
    "frontier_cp": { "curr": -1, "prev": null },
    "reach_cp": {},
    "death_wall": { "curr": null, "prev": null }
  },
  "support_line": "Поддержать проект",
  "updated_at": "1970-01-01T00:00:00Z"
}
